tensorflow_engram/__init__.py
tensorflow_engram/layers.py
tensorflow_engram/models.py
tensorflow_engram/utils.py
tensorflow_engram-0.1.0.dist-info/licenses/LICENSE.md
tensorflow_engram-0.1.0.dist-info/METADATA
tensorflow_engram-0.1.0.dist-info/WHEEL
tensorflow_engram-0.1.0.dist-info/top_level.txt
tensorflow_engram-0.1.0.dist-info/RECORD
