Metadata-Version: 2.4
Name: tensorflow-engram
Version: 0.1.0
Summary: A Python package for Engram Neural Networks, adding biologically-inspired Hebbian memory and engram layers to TensorFlow/Keras models, supporting memory traces, plasticity, attention, and sparsity for neural sequence learning.
Home-page: https://danielathome19.github.io/Engram-Neural-Network
Author: Daniel Szelogowski
Project-URL: Documentation, https://danielathome19.github.io/Engram-Neural-Network
Project-URL: Source, https://github.com/danielathome19/Engram-Neural-Network
Project-URL: Tracker, https://github.com/danielathome19/Engram-Neural-Network/issues
Requires-Python: >=3.12
License-File: LICENSE.md
Dynamic: author
Dynamic: description
Dynamic: description-content-type
Dynamic: home-page
Dynamic: license-file
Dynamic: project-url
Dynamic: requires-python
Dynamic: summary
